{
    "0": "A_o_Nuevo_State_Park.gpx",
    "1": "Alum_Rock_Park_Hike.gpx",
    "2": "Alviso_Marina_Trail_Hike.gpx",
    "3": "Anacapa_Island_Hike.gpx",
    "4": "Angel_Island_.gpx",
    "5": "Angel_Island_Hike.gpx",
    "6": "Bair_Island_Hike.gpx",
    "7": "Bay_Trail_in_Sunnyvale.gpx",
    "8": "Bear_Valley_Trail_Hike_at_Point_Reyes_National_Seashore.gpx",
    "9": "Big_Basin_Buzzard_s_Roost.gpx",
    "10": "Big_Basin_Redwoods_State_Park_Hike.gpx",
    "11": "Black_Mountain_Hike.gpx",
    "12": "Bothe_Napa_Valley_State_Park_Hike.gpx",
    "13": "Capitola_Beach_Walk.gpx",
    "14": "Castle_Rock_State_Park_Hike.gpx",
    "15": "Channel_Islands_National_Park.gpx",
    "16": "Cowell_Purisima_Trail_Hike.gpx",
    "17": "Coyote_Hills_Hike.gpx",
    "18": "Creekside_Park_Walk.gpx",
    "19": "Crissy_Field_to_Fort_Point_Hike.gpx",
    "20": "Cull_Canyon_Hike.gpx",
    "21": "Cupertino_Memorial_Park_Walk.gpx",
    "22": "Dawn_Falls_and_King_Mountain_Loop.gpx",
    "23": "Devil_s_Slide_Trail_and_Pedro_Point_Headlands.gpx",
    "24": "Drakes_Beach_Walk.gpx",
    "25": "Edgewood_County_Park_Hike.gpx",
    "26": "Fifield_Cahill_Ridge_Trail.gpx",
    "27": "Filoli_Tour_Walk.gpx",
    "28": "Fitzgerald_Marine_Hike.gpx",
    "29": "Fort_Ord_Dunes_State_Park.gpx",
    "30": "Fremont_Older_Open_Space_Preserve_Hike.gpx",
    "31": "Garin_Regional_Park_Hike.gpx",
    "32": "Garrapata_State_Park_and_Point_Lobos_State_Reserve_Hike.gpx",
    "33": "Gazos_Creek_State_Beach_Hike.gpx",
    "34": "Golden_Gate_Bridge_to_Black_Sands_Beach_Hike.gpx",
    "35": "Great_America_Walk.gpx",
    "36": "Half_Moon_Bay_Golf_Links_Hike.gpx",
    "37": "Half_Moon_Bay_Hike.gpx",
    "38": "Half_Moon_Bay_Pillar_Point_Hike.gpx",
    "39": "Henry_Cowell_Redwoods_State_Park_Hike.gpx",
    "40": "Hike_in_El_Corte_de_Madera_Creek_Open_Space_Preserve.gpx",
    "41": "Huddart_County_Park_Hike.gpx",
    "42": "Jinan_City_Hike.gpx",
    "43": "John_McLaren_Park_Hike.gpx",
    "44": "Kennedy_Trail_Hike.gpx",
    "45": "Mallard_Slough_Trail.gpx",
    "46": "Marin_Headlands_Hike.gpx",
    "47": "Marin_Headlands_Hike_v2.gpx",
    "48": "Maywood_Park_Walk.gpx",
    "49": "Mission_Peak_Hike.gpx",
    "50": "Mission_Peak_II.gpx",
    "51": "Mori_Point_Hike.gpx",
    "52": "Mt_Tamalpais_Hike.gpx",
    "53": "Muir_Woods_National_Monument_Hike.gpx",
    "54": "Mussel_Rock_Park_Hike.gpx",
    "55": "New_Chicago_Marsh_Trail.gpx",
    "56": "Newark_Slough_Trail.gpx",
    "57": "Ocean_Beach_to_Fort_Funston_to_Thornton_State_Beach.gpx",
    "58": "Palo_Alto_Baylands_Hike.gpx",
    "59": "Phleger_Estate_Hike.gpx",
    "60": "Pinnacles_National_Park_Hike.gpx",
    "61": "Point_Lobos_Hike.gpx",
    "62": "Point_Lobos_State_Reserve_Hike.gpx",
    "63": "Point_Lobos_State_Reserve_v3.gpx",
    "64": "Portalo_Redwoods_State_Park_Hike.gpx",
    "65": "Presidio_of_San_Francisco_Hike.gpx",
    "66": "Priest_Rock_Trail_Hike.gpx",
    "67": "Pulgas_Ridge_Open_Space_Preserve_Hike.gpx",
    "68": "Rancho_Canada_del_Oro_Hike.gpx",
    "69": "Rancho_San_Antonio_Hike.gpx",
    "70": "Redwood_Regional_Park_Hike.gpx",
    "71": "San_Bruno_Mt_Hike.gpx",
    "72": "San_Francisco_Bay_Trail_Hike.gpx",
    "73": "San_Francisco_Coastal_Hike.gpx",
    "74": "San_Pedro_Valley_Hike.gpx",
    "75": "Sanborn_County_Park_Hike.gpx",
    "76": "Santa_Cruz_Coastal_Hike.gpx",
    "77": "Santa_Teresa_Park_Hike.gpx",
    "78": "Sawyer_Camp_Trail_Hike.gpx",
    "79": "SF_Botanical_Garden.gpx",
    "80": "Sharp_Park_Beach_Hike_in_Pacifica.gpx",
    "81": "Stanford_Campus_Hike.gpx",
    "82": "Stanford_Dish_Hike.gpx",
    "83": "Stevens_Creek_County_Park_Hike.gpx",
    "84": "Sunol_Regional_Wilderness_Preserve_Hike.gpx",
    "85": "Sunset_Walk.gpx",
    "86": "Sweeney_Ridge_Milagra_Ridge.gpx",
    "87": "Treasure_Island_Flea_Market.gpx",
    "88": "Ulistac_Natural_Area.gpx",
    "89": "Wilder_Ranch_State_Park_Hike.gpx",
    "90": "Wunderlich_Park_Hike.gpx",
    "numTrails": 91
}